README.md
setup.py
partial_web_file/__init__.py
partial_web_file/__main__.py
partial_web_file/file_util.py
partial_web_file/remote_stream.py
partial_web_file/zip_util.py
partial_web_file.egg-info/PKG-INFO
partial_web_file.egg-info/SOURCES.txt
partial_web_file.egg-info/dependency_links.txt
partial_web_file.egg-info/top_level.txt